{"cameraMode":{"drawMode":0,"name":"Shaded","section":"Shading Mode"},"sceneLighting":true,"audioPlay":false,"sceneViewState":{"m_AlwaysRefresh":false,"showFog":true,"showSkybox":true,"showFlares":true,"showImageEffects":true,"showParticleSystems":true,"showVisualEffectGraphs":true,"m_FxEnabled":true},"in2DMode":false,"pivot":{"x":13.5465087890625,"y":15.039949417114258,"z":-22.868247985839845},"rotation":{"x":-0.25329333543777468,"y":0.46643370389938357,"z":-0.1413816660642624,"w":-0.8356412053108215},"size":1.3717772960662842,"orthographic":false}